kama_sdk/__init__.py
kama_sdk/assets/fail-on-purpose-synopsis.md
kama_sdk/assets/mock-release-note.md
kama_sdk/cli/__init__.py
kama_sdk/cli/cli_helper.py
kama_sdk/cli/console_cli_entrypoint.py
kama_sdk/cli/entrypoint.py
kama_sdk/cli/mocks_cli_entrypoint.py
kama_sdk/cli/server_cli_entrypoint.py
kama_sdk/cli/worker_cli_entrypoint.py
kama_sdk/controllers/__init__.py
kama_sdk/controllers/actions_controller.py
kama_sdk/controllers/app_controller.py
kama_sdk/controllers/ctrl_utils.py
kama_sdk/controllers/health_controller.py
kama_sdk/controllers/injections_controller.py
kama_sdk/controllers/operations_controller.py
kama_sdk/controllers/plugins_controller.py
kama_sdk/controllers/releases_controller.py
kama_sdk/controllers/resources_controller.py
kama_sdk/controllers/status_controller.py
kama_sdk/controllers/telem_controller.py
kama_sdk/controllers/variables_controller.py
kama_sdk/controllers/view_specs_controller.py
kama_sdk/core/__init__.py
kama_sdk/core/core/__init__.py
kama_sdk/core/core/comparison.py
kama_sdk/core/core/config_man.py
kama_sdk/core/core/config_man_helper.py
kama_sdk/core/core/consts.py
kama_sdk/core/core/hub_api_client.py
kama_sdk/core/core/job_client.py
kama_sdk/core/core/plugin_type_defs.py
kama_sdk/core/core/plugins_manager.py
kama_sdk/core/core/presets_man.py
kama_sdk/core/core/status_manager.py
kama_sdk/core/core/str_sub.py
kama_sdk/core/core/structured_search.py
kama_sdk/core/core/types.py
kama_sdk/core/core/updates_man.py
kama_sdk/core/ktea/__init__.py
kama_sdk/core/ktea/http_ktea_client.py
kama_sdk/core/ktea/ktea_client.py
kama_sdk/core/ktea/ktea_provider.py
kama_sdk/core/ktea/local_exec_ktea_client.py
kama_sdk/core/ktea/virtual_ktea_client.py
kama_sdk/core/ktea/vktea_clients_manager.py
kama_sdk/core/telem/__init__.py
kama_sdk/core/telem/backups_manager.py
kama_sdk/core/telem/file_telem_db_delegate.py
kama_sdk/core/telem/flash_helper.py
kama_sdk/core/telem/health_manager.py
kama_sdk/core/telem/telem_manager.py
kama_sdk_py-0.0.31.dist-info/METADATA
kama_sdk_py-0.0.31.dist-info/WHEEL
kama_sdk_py-0.0.31.dist-info/top_level.txt
kama_sdk_py-0.0.31.dist-info/RECORD
