Metadata-Version: 2.1
Name: kama-sdk-py
Version: 0.0.31
Summary: SDK for the Kubernetes Application Management API (KAMA)
Home-page: https://github.com/nectar-cs/kama-sdk-py
Author: NMachine
Author-email: xavier@nmachine.io
License: UNKNOWN
Platform: UNKNOWN
Classifier: Programming Language :: Python :: 3
Classifier: License :: OSI Approved :: MIT License
Classifier: Operating System :: OS Independent
Requires-Python: >=3.8
Requires-Dist: cachetools (>=3.1)
Requires-Dist: flask-cors
Requires-Dist: flask (>=1.1)
Requires-Dist: humanize (>=3.2.0)
Requires-Dist: jq (>=1.1.2)
Requires-Dist: k8kat (>=0.0.246)
Requires-Dist: peewee
Requires-Dist: python-docs-theme
Requires-Dist: redis (>=3)
Requires-Dist: requests
Requires-Dist: rq
Requires-Dist: sphinx-rtd-theme
Requires-Dist: sphinx (>=4.1.2)
Requires-Dist: termcolor (>=1.1.0)
Requires-Dist: validators
